{
	"song": {
		"player1": "bf",
		"player2": "gf-full-invis",
		"notes": [
			{
				"sectionBeats": 2,
				"sectionNotes": [],
				"lengthInSteps": 16,
				"mustHitSection": true,
				"changeBPM": true,
				"bpm": 89
			},
			{
				"sectionNotes": [],
				"lengthInSteps": 16,
				"changeBPM": true,
				"mustHitSection": true,
				"bpm": 110
			},
			{
				"sectionNotes": [],
				"lengthInSteps": 16,
				"bpm": 0,
				"mustHitSection": true
			},
			{
				"sectionNotes": [],
				"lengthInSteps": 16,
				"mustHitSection": true
			},
			{
				"sectionNotes": [],
				"lengthInSteps": 16,
				"changeBPM": false,
				"mustHitSection": true,
				"bpm": 89
			},
			{
				"sectionNotes": [
					[
						10075.5873340143,
						2,
						545.454545454545
					],
					[
						10893.7691521961,
						0,
						0
					],
					[
						11030.1327885598,
						2,
						0
					],
					[
						11166.4964249234,
						1,
						0
					],
					[
						11302.860061287,
						3,
						0
					],
					[
						11439.2236976507,
						1,
						0
					],
					[
						11575.5873340143,
						3,
						272.727272727273
					],
					[
						11984.6782431052,
						0,
						0
					]
				],
				"lengthInSteps": 16,
				"bpm": 110,
				"mustHitSection": true,
				"changeBPM": false
			},
			{
				"sectionNotes": [
					[
						12257.4055158325,
						2,
						136.363636363636
					],
					[
						12461.9509703779,
						1,
						0
					],
					[
						12530.1327885598,
						0,
						136.363636363636
					],
					[
						12802.860061287,
						2,
						0
					],
					[
						12939.2236976507,
						3,
						0
					],
					[
						13075.5873340143,
						0,
						0
					],
					[
						13211.9509703779,
						2,
						0
					],
					[
						13348.3146067416,
						1,
						0
					],
					[
						13484.6782431052,
						3,
						0
					],
					[
						13621.0418794688,
						0,
						0
					],
					[
						13757.4055158325,
						2,
						272.727272727273
					],
					[
						14166.4964249234,
						0,
						0
					]
				],
				"lengthInSteps": 16,
				"bpm": 0,
				"mustHitSection": true
			},
			{
				"sectionNotes": [
					[
						14711.9509703779,
						2,
						0
					],
					[
						14848.3146067416,
						0,
						0
					],
					[
						14984.6782431052,
						3,
						0
					],
					[
						15121.0418794688,
						2,
						0
					],
					[
						15257.4055158325,
						0,
						0
					],
					[
						15393.7691521961,
						1,
						0
					],
					[
						15530.1327885598,
						2,
						136.363636363636
					],
					[
						15802.860061287,
						0,
						0
					],
					[
						15939.2236976507,
						3,
						136.363636363636
					],
					[
						16348.3146067416,
						2,
						136.363636363636
					]
				],
				"lengthInSteps": 16,
				"mustHitSection": true
			},
			{
				"sectionNotes": [
					[
						16893.7691521961,
						1,
						0,
						"Flame_Note"
					],
					[
						16621.0418794688,
						3,
						136.363636363636,
						"Flame_Note"
					],
					[
						17030.1327885598,
						0,
						0,
						"Flame_Note"
					],
					[
						17166.4964249234,
						2,
						0,
						"Flame_Note"
					],
					[
						17371.0418794688,
						0,
						0,
						"Flame_Note"
					],
					[
						17507.4055158325,
						3,
						0,
						"Flame_Note"
					],
					[
						17711.9509703779,
						0,
						0,
						"Flame_Note"
					],
					[
						17848.3146067416,
						3,
						0,
						"Flame_Note"
					],
					[
						18052.860061287,
						1,
						136.363636363636,
						"Flame_Note"
					],
					[
						16893.7691521961,
						2,
						0,
						"Hurt Note"
					],
					[
						16621.0418794688,
						1,
						0,
						"Hurt Note"
					],
					[
						16621.0418794688,
						0,
						0,
						"Hurt Note"
					],
					[
						17166.4964249234,
						3,
						0,
						"Hurt Note"
					],
					[
						17371.0418794688,
						1,
						0,
						"Hurt Note"
					],
					[
						17507.4055158325,
						1,
						0,
						"Hurt Note"
					],
					[
						17507.4055158325,
						2,
						0,
						"Hurt Note"
					],
					[
						17711.9509703779,
						1,
						0,
						"Hurt Note"
					],
					[
						17711.9509703779,
						2,
						0,
						"Hurt Note"
					],
					[
						17848.3146067416,
						2,
						0,
						"Hurt Note"
					],
					[
						18052.860061287,
						0,
						0,
						"Hurt Note"
					],
					[
						18052.860061287,
						2,
						0,
						"Hurt Note"
					],
					[
						18257.4055158325,
						2,
						272.727272727273
					]
				],
				"lengthInSteps": 16,
				"bpm": 0,
				"mustHitSection": true
			},
			{
				"sectionNotes": [
					[
						19075.5873340143,
						2,
						272.727272727273
					],
					[
						19484.6782431052,
						1,
						0
					],
					[
						19893.7691521961,
						2,
						0
					],
					[
						19757.4055158325,
						0,
						0
					],
					[
						19621.0418794688,
						3,
						0
					],
					[
						20030.1327885598,
						0,
						0
					],
					[
						20166.4964249234,
						2,
						0
					],
					[
						20302.860061287,
						1,
						272.727272727273
					]
				],
				"lengthInSteps": 16,
				"mustHitSection": true
			},
			{
				"sectionNotes": [
					[
						21257.4055158325,
						0,
						0
					],
					[
						21189.2236976507,
						3,
						0
					],
					[
						21461.9509703779,
						1,
						0
					],
					[
						21530.1327885598,
						2,
						136.363636363636
					],
					[
						21802.860061287,
						0,
						136.363636363636
					],
					[
						22075.5873340143,
						1,
						136.363636363636
					],
					[
						22348.3146067416,
						2,
						136.363636363636
					],
					[
						22621.0418794688,
						0,
						272.727272727273
					],
					[
						23030.1327885598,
						3,
						0
					]
				],
				"lengthInSteps": 16,
				"bpm": -2147483648,
				"mustHitSection": true
			},
			{
				"sectionNotes": [
					[
						23166.4964249234,
						2,
						136.363636363636
					],
					[
						23439.2236976507,
						0,
						136.363636363636
					],
					[
						23711.9509703779,
						1,
						136.363636363636
					],
					[
						23984.6782431052,
						2,
						136.363636363636
					],
					[
						24257.4055158325,
						0,
						136.363636363636
					],
					[
						24530.1327885598,
						1,
						0
					],
					[
						24666.4964249234,
						2,
						0
					],
					[
						24802.860061287,
						3,
						0
					],
					[
						24939.2236976507,
						1,
						136.363636363636
					],
					[
						24939.2236976507,
						0,
						0,
						"Flame_Note"
					],
					[
						25075.5873340143,
						2,
						0,
						"Flame_Note"
					],
					[
						25211.9509703779,
						3,
						0,
						"Flame_Note"
					]
				],
				"lengthInSteps": 16,
				"mustHitSection": true
			},
			{
				"sectionNotes": [
					[
						25348.3146067416,
						0,
						0,
						"Flame_Note"
					],
					[
						25484.6782431052,
						3,
						0,
						"Flame_Note"
					],
					[
						25621.0418794689,
						1,
						0,
						"Flame_Note"
					],
					[
						25757.4055158325,
						2,
						136.363636363636,
						"Flame_Note"
					],
					[
						26098.3146067416,
						3,
						0,
						"Flame_Note"
					],
					[
						26234.6782431052,
						1,
						0,
						"Flame_Note"
					],
					[
						26439.2236976507,
						0,
						136.363636363636,
						"Flame_Note"
					],
					[
						26711.9509703779,
						2,
						0,
						"Flame_Note"
					],
					[
						26780.1327885598,
						0,
						0,
						"Flame_Note"
					],
					[
						26848.3146067416,
						1,
						0,
						"Flame_Note"
					],
					[
						26711.9509703779,
						3,
						0,
						"Hurt Note"
					],
					[
						26848.3146067416,
						3,
						0,
						"Hurt Note"
					],
					[
						26439.2236976507,
						3,
						0,
						"Hurt Note"
					],
					[
						26098.3146067416,
						0,
						0,
						"Hurt Note"
					],
					[
						25757.4055158325,
						0,
						0,
						"Hurt Note"
					],
					[
						25621.0418794689,
						0,
						0,
						"Hurt Note"
					],
					[
						25416.4964249234,
						2,
						0,
						"Hurt Note"
					],
					[
						26234.6782431052,
						2,
						0,
						"Hurt Note"
					],
					[
						25348.3146067416,
						1,
						0,
						"Hurt Note"
					],
					[
						27189.2236976507,
						1,
						272.727272727273
					]
				],
				"lengthInSteps": 16,
				"bpm": 0,
				"mustHitSection": true
			},
			{
				"sectionNotes": [
					[
						27734.6782431052,
						2,
						0
					],
					[
						27802.860061287,
						3,
						0
					],
					[
						28075.5873340143,
						3,
						0
					],
					[
						28348.3146067416,
						0,
						136.363636363636
					],
					[
						28621.0418794689,
						2,
						0
					],
					[
						28893.7691521961,
						1,
						0
					],
					[
						29030.1327885598,
						0,
						136.363636363636
					],
					[
						29439.2236976507,
						2,
						0
					],
					[
						29575.5873340143,
						3,
						0
					]
				],
				"lengthInSteps": 16,
				"mustHitSection": true
			},
			{
				"sectionNotes": [
					[
						29711.9509703779,
						0,
						0
					],
					[
						29848.3146067416,
						1,
						0
					],
					[
						29984.6782431052,
						2,
						0
					],
					[
						30121.0418794689,
						3,
						0
					],
					[
						30257.4055158325,
						0,
						0
					],
					[
						30530.1327885598,
						3,
						0
					],
					[
						30393.7691521961,
						1,
						0
					],
					[
						30666.4964249234,
						2,
						136.363636363636
					],
					[
						31075.5873340143,
						2,
						0
					],
					[
						31143.7691521961,
						3,
						0
					],
					[
						31280.1327885598,
						0,
						136.363636363636
					],
					[
						31552.860061287,
						2,
						0
					]
				],
				"lengthInSteps": 16,
				"changeBPM": false,
				"mustHitSection": true,
				"bpm": 0
			},
			{
				"sectionNotes": [
					[
						31893.7691521961,
						0,
						136.363636363636
					],
					[
						32166.4964249234,
						3,
						136.363636363636
					],
					[
						32439.2236976507,
						1,
						0
					],
					[
						32643.7691521961,
						2,
						136.363636363636
					],
					[
						32916.4964249234,
						3,
						136.363636363636
					]
				],
				"lengthInSteps": 16,
				"mustHitSection": true
			},
			{
				"sectionNotes": [
					[
						34075.5873340143,
						2,
						0,
						"Flame_Note"
					],
					[
						34348.3146067416,
						0,
						0,
						"Flame_Note"
					],
					[
						34280.1327885598,
						3,
						0,
						"Flame_Note"
					],
					[
						34552.860061287,
						1,
						0,
						"Flame_Note"
					],
					[
						34621.0418794689,
						2,
						0,
						"Flame_Note"
					],
					[
						34825.5873340143,
						0,
						0,
						"Flame_Note"
					],
					[
						34893.7691521961,
						2,
						0,
						"Flame_Note"
					],
					[
						35098.3146067416,
						1,
						0,
						"Flame_Note"
					],
					[
						35166.4964249234,
						0,
						136.363636363636,
						"Flame_Note"
					],
					[
						35371.0418794689,
						3,
						0,
						"Flame_Note"
					],
					[
						35439.2236976507,
						2,
						0,
						"Flame_Note"
					],
					[
						35643.7691521961,
						0,
						0,
						"Flame_Note"
					],
					[
						34893.7691521961,
						3,
						0,
						"Hurt Note"
					],
					[
						34621.0418794689,
						3,
						0,
						"Hurt Note"
					],
					[
						34621.0418794689,
						0,
						0,
						"Hurt Note"
					],
					[
						34348.3146067416,
						2,
						0,
						"Hurt Note"
					],
					[
						34075.5873340143,
						1,
						0,
						"Hurt Note"
					],
					[
						34280.1327885598,
						1,
						0,
						"Hurt Note"
					],
					[
						34552.860061287,
						3,
						0,
						"Hurt Note"
					],
					[
						34825.5873340143,
						1,
						0,
						"Hurt Note"
					],
					[
						35098.3146067416,
						3,
						0,
						"Hurt Note"
					],
					[
						35371.0418794689,
						1,
						0,
						"Hurt Note"
					],
					[
						35643.7691521961,
						3,
						0,
						"Hurt Note"
					],
					[
						35643.7691521961,
						1,
						0,
						"Hurt Note"
					]
				],
				"lengthInSteps": 16,
				"bpm": -2147483648,
				"mustHitSection": true
			},
			{
				"sectionNotes": [],
				"lengthInSteps": 16,
				"mustHitSection": true
			},
			{
				"sectionNotes": [],
				"lengthInSteps": 16,
				"bpm": 0,
				"mustHitSection": true
			},
			{
				"sectionNotes": [],
				"lengthInSteps": 16,
				"mustHitSection": true
			},
			{
				"sectionNotes": [],
				"lengthInSteps": 16,
				"bpm": 0,
				"mustHitSection": true
			},
			{
				"sectionNotes": [],
				"lengthInSteps": 16,
				"mustHitSection": true
			},
			{
				"sectionNotes": [],
				"lengthInSteps": 16,
				"bpm": -2147483648,
				"mustHitSection": true
			},
			{
				"sectionNotes": [],
				"lengthInSteps": 16,
				"mustHitSection": true
			},
			{
				"sectionNotes": [],
				"lengthInSteps": 16,
				"bpm": 0,
				"mustHitSection": true
			},
			{
				"sectionNotes": [],
				"lengthInSteps": 16,
				"mustHitSection": true
			},
			{
				"sectionNotes": [],
				"lengthInSteps": 16,
				"bpm": 0,
				"mustHitSection": true
			},
			{
				"sectionNotes": [],
				"lengthInSteps": 16,
				"mustHitSection": true
			},
			{
				"sectionNotes": [],
				"lengthInSteps": 16,
				"bpm": -2147483648,
				"mustHitSection": true
			},
			{
				"sectionNotes": [],
				"lengthInSteps": 16,
				"bpm": 0,
				"mustHitSection": true
			},
			{
				"sectionNotes": [],
				"lengthInSteps": 16,
				"bpm": 0,
				"mustHitSection": true
			},
			{
				"sectionNotes": [],
				"lengthInSteps": 16,
				"bpm": 0,
				"mustHitSection": true
			},
			{
				"sectionNotes": [],
				"lengthInSteps": 16,
				"mustHitSection": true
			},
			{
				"sectionNotes": [],
				"lengthInSteps": 16,
				"bpm": 0,
				"mustHitSection": true
			},
			{
				"sectionNotes": [],
				"lengthInSteps": 16,
				"mustHitSection": true,
				"bpm": 710,
				"changeBPM": false
			},
			{
				"sectionNotes": [],
				"lengthInSteps": 16,
				"mustHitSection": true
			},
			{
				"sectionNotes": [],
				"lengthInSteps": 16,
				"mustHitSection": true
			},
			{
				"sectionNotes": [],
				"lengthInSteps": 16,
				"mustHitSection": true
			},
			{
				"sectionNotes": [],
				"lengthInSteps": 16,
				"mustHitSection": true
			},
			{
				"sectionNotes": [],
				"lengthInSteps": 16,
				"mustHitSection": true
			},
			{
				"sectionNotes": [],
				"lengthInSteps": 16,
				"mustHitSection": true
			},
			{
				"sectionNotes": [],
				"lengthInSteps": 16,
				"mustHitSection": true
			},
			{
				"sectionNotes": [],
				"lengthInSteps": 16,
				"mustHitSection": true
			},
			{
				"sectionNotes": [],
				"lengthInSteps": 16,
				"mustHitSection": true
			},
			{
				"sectionNotes": [],
				"lengthInSteps": 16,
				"mustHitSection": true
			},
			{
				"sectionNotes": [],
				"lengthInSteps": 16,
				"mustHitSection": true
			},
			{
				"sectionNotes": [],
				"lengthInSteps": 16,
				"mustHitSection": true
			},
			{
				"sectionNotes": [],
				"lengthInSteps": 16,
				"mustHitSection": true
			},
			{
				"sectionNotes": [],
				"lengthInSteps": 16,
				"mustHitSection": true
			},
			{
				"sectionNotes": [],
				"lengthInSteps": 16,
				"mustHitSection": true
			},
			{
				"sectionNotes": [],
				"lengthInSteps": 16,
				"mustHitSection": true
			},
			{
				"sectionNotes": [],
				"lengthInSteps": 16,
				"mustHitSection": true
			},
			{
				"sectionNotes": [],
				"lengthInSteps": 16,
				"mustHitSection": true
			},
			{
				"sectionNotes": [],
				"lengthInSteps": 16,
				"mustHitSection": true
			},
			{
				"sectionNotes": [],
				"lengthInSteps": 16,
				"mustHitSection": true
			},
			{
				"sectionNotes": [],
				"lengthInSteps": 16,
				"mustHitSection": true
			},
			{
				"sectionNotes": [],
				"lengthInSteps": 16,
				"mustHitSection": true
			},
			{
				"sectionNotes": [],
				"lengthInSteps": 16,
				"mustHitSection": true
			},
			{
				"sectionNotes": [],
				"lengthInSteps": 16,
				"mustHitSection": true
			},
			{
				"sectionNotes": [],
				"lengthInSteps": 16,
				"mustHitSection": true
			},
			{
				"sectionNotes": [],
				"lengthInSteps": 16,
				"mustHitSection": true
			},
			{
				"sectionNotes": [],
				"lengthInSteps": 16,
				"mustHitSection": true
			},
			{
				"sectionNotes": [],
				"lengthInSteps": 16,
				"mustHitSection": true
			},
			{
				"sectionNotes": [],
				"lengthInSteps": 16,
				"mustHitSection": true
			},
			{
				"sectionNotes": [],
				"lengthInSteps": 16,
				"mustHitSection": true
			},
			{
				"lengthInSteps": 16,
				"typeOfSection": 0,
				"sectionNotes": [],
				"altAnim": false,
				"bpm": 180,
				"changeBPM": false,
				"mustHitSection": true
			},
			{
				"sectionNotes": [],
				"typeOfSection": 0,
				"lengthInSteps": 16,
				"altAnim": false,
				"mustHitSection": true,
				"changeBPM": false,
				"bpm": 180
			},
			{
				"lengthInSteps": 16,
				"typeOfSection": 0,
				"sectionNotes": [],
				"altAnim": false,
				"bpm": 350,
				"changeBPM": false,
				"mustHitSection": true
			},
			{
				"lengthInSteps": 16,
				"typeOfSection": 0,
				"sectionNotes": [],
				"altAnim": false,
				"bpm": 35,
				"changeBPM": false,
				"mustHitSection": true
			},
			{
				"lengthInSteps": 16,
				"typeOfSection": 0,
				"sectionNotes": [],
				"altAnim": false,
				"bpm": 350,
				"changeBPM": false,
				"mustHitSection": true
			},
			{
				"lengthInSteps": 16,
				"typeOfSection": 0,
				"sectionNotes": [],
				"altAnim": false,
				"bpm": 350,
				"changeBPM": false,
				"mustHitSection": true
			},
			{
				"lengthInSteps": 16,
				"typeOfSection": 0,
				"sectionNotes": [],
				"altAnim": false,
				"bpm": 350,
				"changeBPM": false,
				"mustHitSection": true
			},
			{
				"lengthInSteps": 16,
				"typeOfSection": 0,
				"sectionNotes": [],
				"altAnim": false,
				"bpm": 350,
				"changeBPM": false,
				"mustHitSection": true
			},
			{
				"lengthInSteps": 16,
				"typeOfSection": 0,
				"sectionNotes": [],
				"altAnim": false,
				"bpm": 350,
				"changeBPM": false,
				"mustHitSection": true
			},
			{
				"lengthInSteps": 16,
				"typeOfSection": 0,
				"sectionNotes": [],
				"altAnim": false,
				"bpm": 350,
				"changeBPM": false,
				"mustHitSection": true
			},
			{
				"lengthInSteps": 16,
				"typeOfSection": 0,
				"sectionNotes": [],
				"altAnim": false,
				"bpm": 350,
				"changeBPM": false,
				"mustHitSection": true
			},
			{
				"lengthInSteps": 16,
				"typeOfSection": 0,
				"sectionNotes": [],
				"altAnim": false,
				"bpm": 350,
				"changeBPM": false,
				"mustHitSection": true
			},
			{
				"lengthInSteps": 16,
				"typeOfSection": 0,
				"sectionNotes": [],
				"altAnim": false,
				"bpm": 350,
				"changeBPM": false,
				"mustHitSection": true
			},
			{
				"lengthInSteps": 16,
				"typeOfSection": 0,
				"sectionNotes": [],
				"altAnim": false,
				"bpm": 350,
				"changeBPM": false,
				"mustHitSection": true
			},
			{
				"lengthInSteps": 16,
				"typeOfSection": 0,
				"sectionNotes": [],
				"altAnim": false,
				"bpm": 350,
				"changeBPM": false,
				"mustHitSection": true
			},
			{
				"lengthInSteps": 16,
				"typeOfSection": 0,
				"sectionNotes": [],
				"altAnim": false,
				"bpm": 350,
				"changeBPM": false,
				"mustHitSection": true
			},
			{
				"lengthInSteps": 16,
				"typeOfSection": 0,
				"sectionNotes": [],
				"altAnim": false,
				"bpm": 350,
				"changeBPM": false,
				"mustHitSection": true
			},
			{
				"lengthInSteps": 16,
				"typeOfSection": 0,
				"sectionNotes": [],
				"altAnim": false,
				"bpm": 350,
				"changeBPM": false,
				"mustHitSection": true
			},
			{
				"lengthInSteps": 16,
				"typeOfSection": 0,
				"sectionNotes": [],
				"altAnim": false,
				"bpm": 350,
				"changeBPM": false,
				"mustHitSection": true
			},
			{
				"lengthInSteps": 16,
				"typeOfSection": 0,
				"sectionNotes": [],
				"altAnim": false,
				"bpm": 350,
				"changeBPM": false,
				"mustHitSection": true
			},
			{
				"lengthInSteps": 16,
				"typeOfSection": 0,
				"sectionNotes": [],
				"altAnim": false,
				"bpm": 350,
				"changeBPM": false,
				"mustHitSection": true
			},
			{
				"lengthInSteps": 16,
				"typeOfSection": 0,
				"sectionNotes": [],
				"altAnim": false,
				"bpm": 350,
				"changeBPM": false,
				"mustHitSection": true
			},
			{
				"lengthInSteps": 16,
				"typeOfSection": 0,
				"sectionNotes": [],
				"altAnim": false,
				"bpm": 350,
				"changeBPM": false,
				"mustHitSection": true
			},
			{
				"lengthInSteps": 16,
				"typeOfSection": 0,
				"sectionNotes": [],
				"altAnim": false,
				"bpm": 350,
				"changeBPM": false,
				"mustHitSection": true
			},
			{
				"lengthInSteps": 16,
				"typeOfSection": 0,
				"sectionNotes": [],
				"altAnim": false,
				"bpm": 350,
				"changeBPM": false,
				"mustHitSection": true
			},
			{
				"lengthInSteps": 16,
				"typeOfSection": 0,
				"sectionNotes": [],
				"altAnim": false,
				"bpm": 350,
				"changeBPM": false,
				"mustHitSection": true
			},
			{
				"lengthInSteps": 16,
				"typeOfSection": 0,
				"sectionNotes": [],
				"altAnim": false,
				"bpm": 350,
				"changeBPM": false,
				"mustHitSection": true
			},
			{
				"lengthInSteps": 16,
				"typeOfSection": 0,
				"sectionNotes": [],
				"altAnim": false,
				"bpm": 350,
				"changeBPM": false,
				"mustHitSection": true
			},
			{
				"lengthInSteps": 16,
				"typeOfSection": 0,
				"sectionNotes": [],
				"altAnim": false,
				"bpm": 350,
				"changeBPM": false,
				"mustHitSection": true
			},
			{
				"lengthInSteps": 16,
				"typeOfSection": 0,
				"sectionNotes": [],
				"altAnim": false,
				"bpm": 350,
				"changeBPM": false,
				"mustHitSection": true
			},
			{
				"lengthInSteps": 16,
				"typeOfSection": 0,
				"sectionNotes": [],
				"altAnim": false,
				"bpm": 350,
				"changeBPM": false,
				"mustHitSection": true
			},
			{
				"lengthInSteps": 16,
				"typeOfSection": 0,
				"sectionNotes": [],
				"altAnim": false,
				"bpm": 350,
				"changeBPM": false,
				"mustHitSection": true
			},
			{
				"lengthInSteps": 16,
				"typeOfSection": 0,
				"sectionNotes": [],
				"altAnim": false,
				"bpm": 350,
				"changeBPM": false,
				"mustHitSection": true
			},
			{
				"lengthInSteps": 16,
				"typeOfSection": 0,
				"sectionNotes": [],
				"altAnim": false,
				"bpm": 350,
				"changeBPM": false,
				"mustHitSection": true
			},
			{
				"lengthInSteps": 16,
				"typeOfSection": 0,
				"sectionNotes": [],
				"altAnim": false,
				"bpm": 350,
				"changeBPM": false,
				"mustHitSection": true
			},
			{
				"lengthInSteps": 16,
				"typeOfSection": 0,
				"sectionNotes": [],
				"altAnim": false,
				"bpm": 350,
				"changeBPM": false,
				"mustHitSection": true
			},
			{
				"lengthInSteps": 16,
				"typeOfSection": 0,
				"sectionNotes": [],
				"altAnim": false,
				"bpm": 350,
				"changeBPM": false,
				"mustHitSection": true
			},
			{
				"lengthInSteps": 16,
				"typeOfSection": 0,
				"sectionNotes": [],
				"altAnim": false,
				"bpm": 350,
				"changeBPM": false,
				"mustHitSection": true
			},
			{
				"lengthInSteps": 16,
				"typeOfSection": 0,
				"sectionNotes": [],
				"altAnim": false,
				"bpm": 350,
				"changeBPM": false,
				"mustHitSection": true
			},
			{
				"lengthInSteps": 16,
				"typeOfSection": 0,
				"sectionNotes": [],
				"altAnim": false,
				"bpm": 350,
				"changeBPM": false,
				"mustHitSection": true
			},
			{
				"lengthInSteps": 16,
				"typeOfSection": 0,
				"sectionNotes": [],
				"altAnim": false,
				"bpm": 350,
				"changeBPM": false,
				"mustHitSection": true
			},
			{
				"lengthInSteps": 16,
				"typeOfSection": 0,
				"sectionNotes": [],
				"altAnim": false,
				"bpm": 350,
				"changeBPM": false,
				"mustHitSection": true
			},
			{
				"lengthInSteps": 16,
				"typeOfSection": 0,
				"sectionNotes": [],
				"altAnim": false,
				"bpm": 350,
				"changeBPM": false,
				"mustHitSection": true
			},
			{
				"lengthInSteps": 16,
				"typeOfSection": 0,
				"sectionNotes": [],
				"altAnim": false,
				"bpm": 350,
				"changeBPM": false,
				"mustHitSection": true
			},
			{
				"lengthInSteps": 16,
				"typeOfSection": 0,
				"sectionNotes": [],
				"altAnim": false,
				"bpm": 350,
				"changeBPM": false,
				"mustHitSection": true
			},
			{
				"lengthInSteps": 16,
				"typeOfSection": 0,
				"sectionNotes": [],
				"altAnim": false,
				"bpm": 350,
				"changeBPM": false,
				"mustHitSection": true
			},
			{
				"lengthInSteps": 16,
				"typeOfSection": 0,
				"sectionNotes": [],
				"altAnim": false,
				"bpm": 350,
				"changeBPM": false,
				"mustHitSection": true
			},
			{
				"lengthInSteps": 16,
				"typeOfSection": 0,
				"sectionNotes": [],
				"altAnim": false,
				"bpm": 350,
				"changeBPM": false,
				"mustHitSection": true
			},
			{
				"lengthInSteps": 16,
				"typeOfSection": 0,
				"sectionNotes": [],
				"altAnim": false,
				"bpm": 350,
				"changeBPM": false,
				"mustHitSection": true
			},
			{
				"lengthInSteps": 16,
				"typeOfSection": 0,
				"sectionNotes": [],
				"altAnim": false,
				"bpm": 350,
				"changeBPM": false,
				"mustHitSection": true
			},
			{
				"lengthInSteps": 16,
				"typeOfSection": 0,
				"sectionNotes": [],
				"altAnim": false,
				"bpm": 350,
				"changeBPM": false,
				"mustHitSection": true
			},
			{
				"lengthInSteps": 16,
				"typeOfSection": 0,
				"sectionNotes": [],
				"altAnim": false,
				"bpm": 350,
				"changeBPM": false,
				"mustHitSection": true
			},
			{
				"lengthInSteps": 16,
				"typeOfSection": 0,
				"sectionNotes": [],
				"altAnim": false,
				"bpm": 350,
				"changeBPM": false,
				"mustHitSection": true
			},
			{
				"lengthInSteps": 16,
				"typeOfSection": 0,
				"sectionNotes": [],
				"altAnim": false,
				"bpm": 350,
				"changeBPM": false,
				"mustHitSection": true
			},
			{
				"lengthInSteps": 16,
				"typeOfSection": 0,
				"sectionNotes": [],
				"altAnim": false,
				"bpm": 350,
				"changeBPM": false,
				"mustHitSection": true
			},
			{
				"lengthInSteps": 16,
				"typeOfSection": 0,
				"sectionNotes": [],
				"altAnim": false,
				"bpm": 350,
				"changeBPM": false,
				"mustHitSection": true
			},
			{
				"lengthInSteps": 16,
				"typeOfSection": 0,
				"sectionNotes": [],
				"altAnim": false,
				"bpm": 350,
				"changeBPM": false,
				"mustHitSection": true
			},
			{
				"lengthInSteps": 16,
				"typeOfSection": 0,
				"sectionNotes": [],
				"altAnim": false,
				"bpm": 350,
				"changeBPM": false,
				"mustHitSection": true
			},
			{
				"lengthInSteps": 16,
				"typeOfSection": 0,
				"sectionNotes": [],
				"altAnim": false,
				"bpm": 350,
				"changeBPM": false,
				"mustHitSection": true
			},
			{
				"lengthInSteps": 16,
				"typeOfSection": 0,
				"sectionNotes": [],
				"altAnim": false,
				"bpm": 350,
				"changeBPM": false,
				"mustHitSection": true
			},
			{
				"lengthInSteps": 16,
				"typeOfSection": 0,
				"sectionNotes": [],
				"altAnim": false,
				"bpm": 350,
				"changeBPM": false,
				"mustHitSection": true
			},
			{
				"lengthInSteps": 16,
				"typeOfSection": 0,
				"sectionNotes": [],
				"altAnim": false,
				"bpm": 350,
				"changeBPM": false,
				"mustHitSection": true
			},
			{
				"lengthInSteps": 16,
				"typeOfSection": 0,
				"sectionNotes": [],
				"altAnim": false,
				"bpm": 350,
				"changeBPM": false,
				"mustHitSection": true
			},
			{
				"lengthInSteps": 16,
				"typeOfSection": 0,
				"sectionNotes": [],
				"altAnim": false,
				"bpm": 350,
				"changeBPM": false,
				"mustHitSection": true
			},
			{
				"lengthInSteps": 16,
				"typeOfSection": 0,
				"sectionNotes": [],
				"altAnim": false,
				"bpm": 360,
				"changeBPM": false,
				"mustHitSection": true
			},
			{
				"lengthInSteps": 16,
				"typeOfSection": 0,
				"sectionNotes": [],
				"altAnim": false,
				"bpm": 360,
				"changeBPM": false,
				"mustHitSection": true
			},
			{
				"lengthInSteps": 16,
				"typeOfSection": 0,
				"sectionNotes": [],
				"altAnim": false,
				"bpm": 360,
				"changeBPM": false,
				"mustHitSection": true
			},
			{
				"lengthInSteps": 16,
				"typeOfSection": 0,
				"sectionNotes": [],
				"altAnim": false,
				"bpm": 360,
				"changeBPM": false,
				"mustHitSection": true
			},
			{
				"lengthInSteps": 16,
				"typeOfSection": 0,
				"sectionNotes": [],
				"altAnim": false,
				"bpm": 360,
				"changeBPM": false,
				"mustHitSection": true
			},
			{
				"lengthInSteps": 16,
				"typeOfSection": 0,
				"sectionNotes": [],
				"altAnim": false,
				"bpm": 360,
				"changeBPM": false,
				"mustHitSection": true
			},
			{
				"lengthInSteps": 16,
				"typeOfSection": 0,
				"sectionNotes": [],
				"altAnim": false,
				"bpm": 360,
				"changeBPM": false,
				"mustHitSection": true
			},
			{
				"lengthInSteps": 16,
				"typeOfSection": 0,
				"sectionNotes": [],
				"altAnim": false,
				"bpm": 360,
				"changeBPM": false,
				"mustHitSection": true
			},
			{
				"lengthInSteps": 16,
				"typeOfSection": 0,
				"sectionNotes": [],
				"altAnim": false,
				"bpm": 360,
				"changeBPM": false,
				"mustHitSection": true
			},
			{
				"lengthInSteps": 16,
				"typeOfSection": 0,
				"sectionNotes": [],
				"altAnim": false,
				"bpm": 360,
				"changeBPM": false,
				"mustHitSection": true
			},
			{
				"lengthInSteps": 16,
				"typeOfSection": 0,
				"sectionNotes": [],
				"altAnim": false,
				"bpm": 360,
				"changeBPM": false,
				"mustHitSection": true
			},
			{
				"lengthInSteps": 16,
				"typeOfSection": 0,
				"sectionNotes": [],
				"altAnim": false,
				"bpm": 360,
				"changeBPM": false,
				"mustHitSection": true
			},
			{
				"lengthInSteps": 16,
				"typeOfSection": 0,
				"sectionNotes": [],
				"altAnim": false,
				"bpm": 360,
				"changeBPM": false,
				"mustHitSection": true
			},
			{
				"lengthInSteps": 16,
				"typeOfSection": 0,
				"sectionNotes": [],
				"altAnim": false,
				"bpm": 360,
				"changeBPM": false,
				"mustHitSection": true
			},
			{
				"lengthInSteps": 16,
				"typeOfSection": 0,
				"sectionNotes": [],
				"altAnim": false,
				"bpm": 360,
				"changeBPM": false,
				"mustHitSection": true
			},
			{
				"lengthInSteps": 16,
				"typeOfSection": 0,
				"sectionNotes": [],
				"altAnim": false,
				"bpm": 360,
				"changeBPM": false,
				"mustHitSection": true
			},
			{
				"lengthInSteps": 16,
				"typeOfSection": 0,
				"sectionNotes": [],
				"altAnim": false,
				"bpm": 360,
				"changeBPM": false,
				"mustHitSection": true
			},
			{
				"lengthInSteps": 16,
				"typeOfSection": 0,
				"sectionNotes": [],
				"altAnim": false,
				"bpm": 360,
				"changeBPM": false,
				"mustHitSection": true
			},
			{
				"lengthInSteps": 16,
				"typeOfSection": 0,
				"sectionNotes": [],
				"altAnim": false,
				"bpm": 360,
				"changeBPM": false,
				"mustHitSection": true
			},
			{
				"lengthInSteps": 16,
				"typeOfSection": 0,
				"sectionNotes": [],
				"altAnim": false,
				"bpm": 360,
				"changeBPM": false,
				"mustHitSection": true
			},
			{
				"lengthInSteps": 16,
				"typeOfSection": 0,
				"sectionNotes": [],
				"altAnim": false,
				"bpm": 360,
				"changeBPM": false,
				"mustHitSection": true
			},
			{
				"lengthInSteps": 16,
				"typeOfSection": 0,
				"sectionNotes": [],
				"altAnim": false,
				"bpm": 360,
				"changeBPM": false,
				"mustHitSection": true
			},
			{
				"lengthInSteps": 16,
				"typeOfSection": 0,
				"sectionNotes": [],
				"altAnim": false,
				"bpm": 360,
				"changeBPM": false,
				"mustHitSection": true
			},
			{
				"lengthInSteps": 16,
				"typeOfSection": 0,
				"sectionNotes": [],
				"altAnim": false,
				"bpm": 360,
				"changeBPM": false,
				"mustHitSection": true
			},
			{
				"lengthInSteps": 16,
				"typeOfSection": 0,
				"sectionNotes": [],
				"altAnim": false,
				"bpm": 360,
				"changeBPM": false,
				"mustHitSection": true
			},
			{
				"lengthInSteps": 16,
				"typeOfSection": 0,
				"sectionNotes": [],
				"altAnim": false,
				"bpm": 360,
				"changeBPM": false,
				"mustHitSection": true
			},
			{
				"lengthInSteps": 16,
				"typeOfSection": 0,
				"sectionNotes": [],
				"altAnim": false,
				"bpm": 360,
				"changeBPM": false,
				"mustHitSection": true
			},
			{
				"lengthInSteps": 16,
				"typeOfSection": 0,
				"sectionNotes": [],
				"altAnim": false,
				"bpm": 360,
				"changeBPM": false,
				"mustHitSection": true
			},
			{
				"lengthInSteps": 16,
				"typeOfSection": 0,
				"sectionNotes": [],
				"altAnim": false,
				"bpm": 360,
				"changeBPM": false,
				"mustHitSection": true
			},
			{
				"lengthInSteps": 16,
				"typeOfSection": 0,
				"sectionNotes": [],
				"altAnim": false,
				"bpm": 360,
				"changeBPM": false,
				"mustHitSection": true
			},
			{
				"lengthInSteps": 16,
				"typeOfSection": 0,
				"sectionNotes": [],
				"altAnim": false,
				"bpm": 360,
				"changeBPM": false,
				"mustHitSection": true
			},
			{
				"lengthInSteps": 16,
				"typeOfSection": 0,
				"sectionNotes": [],
				"altAnim": false,
				"bpm": 360,
				"changeBPM": false,
				"mustHitSection": true
			},
			{
				"lengthInSteps": 16,
				"typeOfSection": 0,
				"sectionNotes": [],
				"altAnim": false,
				"bpm": 360,
				"changeBPM": false,
				"mustHitSection": true
			},
			{
				"lengthInSteps": 16,
				"typeOfSection": 0,
				"sectionNotes": [],
				"altAnim": false,
				"bpm": 360,
				"changeBPM": false,
				"mustHitSection": true
			},
			{
				"lengthInSteps": 16,
				"typeOfSection": 0,
				"sectionNotes": [],
				"altAnim": false,
				"bpm": 360,
				"changeBPM": false,
				"mustHitSection": true
			},
			{
				"lengthInSteps": 16,
				"typeOfSection": 0,
				"sectionNotes": [],
				"altAnim": false,
				"bpm": 360,
				"changeBPM": false,
				"mustHitSection": true
			},
			{
				"lengthInSteps": 16,
				"typeOfSection": 0,
				"sectionNotes": [],
				"altAnim": false,
				"bpm": 360,
				"changeBPM": false,
				"mustHitSection": true
			},
			{
				"lengthInSteps": 16,
				"typeOfSection": 0,
				"sectionNotes": [],
				"altAnim": false,
				"bpm": 360,
				"changeBPM": false,
				"mustHitSection": true
			},
			{
				"lengthInSteps": 16,
				"typeOfSection": 0,
				"sectionNotes": [],
				"altAnim": false,
				"bpm": 360,
				"changeBPM": false,
				"mustHitSection": true
			},
			{
				"lengthInSteps": 16,
				"typeOfSection": 0,
				"sectionNotes": [],
				"altAnim": false,
				"bpm": 360,
				"changeBPM": false,
				"mustHitSection": true
			},
			{
				"lengthInSteps": 16,
				"typeOfSection": 0,
				"sectionNotes": [],
				"altAnim": false,
				"bpm": 360,
				"changeBPM": false,
				"mustHitSection": true
			},
			{
				"lengthInSteps": 16,
				"typeOfSection": 0,
				"sectionNotes": [],
				"altAnim": false,
				"bpm": 360,
				"changeBPM": false,
				"mustHitSection": true
			},
			{
				"lengthInSteps": 16,
				"typeOfSection": 0,
				"sectionNotes": [],
				"altAnim": false,
				"bpm": 360,
				"changeBPM": false,
				"mustHitSection": true
			},
			{
				"lengthInSteps": 16,
				"typeOfSection": 0,
				"sectionNotes": [],
				"altAnim": false,
				"bpm": 360,
				"changeBPM": false,
				"mustHitSection": true
			},
			{
				"lengthInSteps": 16,
				"typeOfSection": 0,
				"sectionNotes": [],
				"altAnim": false,
				"bpm": 360,
				"changeBPM": false,
				"mustHitSection": true
			},
			{
				"lengthInSteps": 16,
				"typeOfSection": 0,
				"sectionNotes": [],
				"altAnim": false,
				"bpm": 360,
				"changeBPM": false,
				"mustHitSection": true
			},
			{
				"lengthInSteps": 16,
				"typeOfSection": 0,
				"sectionNotes": [],
				"altAnim": false,
				"bpm": 360,
				"changeBPM": false,
				"mustHitSection": true
			},
			{
				"lengthInSteps": 16,
				"typeOfSection": 0,
				"sectionNotes": [],
				"altAnim": false,
				"bpm": 360,
				"changeBPM": false,
				"mustHitSection": true
			},
			{
				"lengthInSteps": 16,
				"typeOfSection": 0,
				"sectionNotes": [],
				"altAnim": false,
				"bpm": 360,
				"changeBPM": false,
				"mustHitSection": true
			},
			{
				"lengthInSteps": 16,
				"typeOfSection": 0,
				"sectionNotes": [],
				"altAnim": false,
				"bpm": 360,
				"changeBPM": false,
				"mustHitSection": true
			},
			{
				"lengthInSteps": 16,
				"typeOfSection": 0,
				"sectionNotes": [],
				"altAnim": false,
				"bpm": 360,
				"changeBPM": false,
				"mustHitSection": true
			},
			{
				"lengthInSteps": 16,
				"typeOfSection": 0,
				"sectionNotes": [],
				"altAnim": false,
				"bpm": 360,
				"changeBPM": false,
				"mustHitSection": true
			},
			{
				"lengthInSteps": 16,
				"typeOfSection": 0,
				"sectionNotes": [],
				"altAnim": false,
				"bpm": 360,
				"changeBPM": false,
				"mustHitSection": true
			},
			{
				"lengthInSteps": 16,
				"typeOfSection": 0,
				"sectionNotes": [],
				"altAnim": false,
				"bpm": 360,
				"changeBPM": false,
				"mustHitSection": true
			},
			{
				"lengthInSteps": 16,
				"typeOfSection": 0,
				"sectionNotes": [],
				"altAnim": false,
				"bpm": 360,
				"changeBPM": false,
				"mustHitSection": true
			},
			{
				"lengthInSteps": 16,
				"typeOfSection": 0,
				"sectionNotes": [],
				"altAnim": false,
				"bpm": 360,
				"changeBPM": false,
				"mustHitSection": true
			},
			{
				"lengthInSteps": 16,
				"typeOfSection": 0,
				"sectionNotes": [],
				"altAnim": false,
				"bpm": 360,
				"changeBPM": false,
				"mustHitSection": true
			},
			{
				"lengthInSteps": 16,
				"typeOfSection": 0,
				"sectionNotes": [],
				"altAnim": false,
				"bpm": 360,
				"changeBPM": false,
				"mustHitSection": true
			},
			{
				"lengthInSteps": 16,
				"typeOfSection": 0,
				"sectionNotes": [],
				"altAnim": false,
				"bpm": 360,
				"changeBPM": false,
				"mustHitSection": true
			},
			{
				"lengthInSteps": 16,
				"typeOfSection": 0,
				"sectionNotes": [],
				"altAnim": false,
				"bpm": 360,
				"changeBPM": false,
				"mustHitSection": true
			},
			{
				"lengthInSteps": 16,
				"typeOfSection": 0,
				"sectionNotes": [],
				"altAnim": false,
				"bpm": 360,
				"changeBPM": false,
				"mustHitSection": true
			},
			{
				"lengthInSteps": 16,
				"typeOfSection": 0,
				"sectionNotes": [],
				"altAnim": false,
				"bpm": 360,
				"changeBPM": false,
				"mustHitSection": true
			},
			{
				"lengthInSteps": 16,
				"typeOfSection": 0,
				"sectionNotes": [],
				"altAnim": false,
				"bpm": 360,
				"changeBPM": false,
				"mustHitSection": true
			},
			{
				"lengthInSteps": 16,
				"typeOfSection": 0,
				"sectionNotes": [],
				"altAnim": false,
				"bpm": 360,
				"changeBPM": false,
				"mustHitSection": true
			},
			{
				"lengthInSteps": 16,
				"typeOfSection": 0,
				"sectionNotes": [],
				"altAnim": false,
				"bpm": 360,
				"changeBPM": false,
				"mustHitSection": true
			},
			{
				"lengthInSteps": 16,
				"typeOfSection": 0,
				"sectionNotes": [],
				"altAnim": false,
				"bpm": 360,
				"changeBPM": false,
				"mustHitSection": true
			},
			{
				"lengthInSteps": 16,
				"typeOfSection": 0,
				"sectionNotes": [],
				"altAnim": false,
				"bpm": 360,
				"changeBPM": false,
				"mustHitSection": true
			},
			{
				"lengthInSteps": 16,
				"typeOfSection": 0,
				"sectionNotes": [],
				"altAnim": false,
				"bpm": 360,
				"changeBPM": false,
				"mustHitSection": true
			},
			{
				"lengthInSteps": 16,
				"typeOfSection": 0,
				"sectionNotes": [],
				"altAnim": false,
				"bpm": 360,
				"changeBPM": false,
				"mustHitSection": true
			},
			{
				"lengthInSteps": 16,
				"typeOfSection": 0,
				"sectionNotes": [],
				"altAnim": false,
				"bpm": 360,
				"changeBPM": false,
				"mustHitSection": true
			},
			{
				"lengthInSteps": 16,
				"typeOfSection": 0,
				"sectionNotes": [],
				"altAnim": false,
				"bpm": 360,
				"changeBPM": false,
				"mustHitSection": true
			},
			{
				"lengthInSteps": 16,
				"typeOfSection": 0,
				"sectionNotes": [],
				"altAnim": false,
				"bpm": 360,
				"changeBPM": false,
				"mustHitSection": true
			},
			{
				"lengthInSteps": 16,
				"typeOfSection": 0,
				"sectionNotes": [],
				"altAnim": false,
				"bpm": 360,
				"changeBPM": false,
				"mustHitSection": true
			},
			{
				"lengthInSteps": 16,
				"typeOfSection": 0,
				"sectionNotes": [],
				"altAnim": false,
				"bpm": 360,
				"changeBPM": false,
				"mustHitSection": true
			},
			{
				"lengthInSteps": 16,
				"typeOfSection": 0,
				"sectionNotes": [],
				"altAnim": false,
				"bpm": 360,
				"changeBPM": false,
				"mustHitSection": true
			},
			{
				"lengthInSteps": 16,
				"typeOfSection": 0,
				"sectionNotes": [],
				"altAnim": false,
				"bpm": 360,
				"changeBPM": false,
				"mustHitSection": true
			},
			{
				"lengthInSteps": 16,
				"typeOfSection": 0,
				"sectionNotes": [],
				"altAnim": false,
				"bpm": 360,
				"changeBPM": false,
				"mustHitSection": true
			},
			{
				"lengthInSteps": 16,
				"typeOfSection": 0,
				"sectionNotes": [],
				"altAnim": false,
				"bpm": 360,
				"changeBPM": false,
				"mustHitSection": true
			},
			{
				"lengthInSteps": 16,
				"typeOfSection": 0,
				"sectionNotes": [],
				"altAnim": false,
				"bpm": 360,
				"changeBPM": false,
				"mustHitSection": true
			},
			{
				"lengthInSteps": 16,
				"typeOfSection": 0,
				"sectionNotes": [],
				"altAnim": false,
				"bpm": 360,
				"changeBPM": false,
				"mustHitSection": true
			},
			{
				"lengthInSteps": 16,
				"typeOfSection": 0,
				"sectionNotes": [],
				"altAnim": false,
				"bpm": 360,
				"changeBPM": false,
				"mustHitSection": true
			},
			{
				"lengthInSteps": 16,
				"typeOfSection": 0,
				"sectionNotes": [],
				"altAnim": false,
				"bpm": 360,
				"changeBPM": false,
				"mustHitSection": true
			},
			{
				"lengthInSteps": 16,
				"typeOfSection": 0,
				"sectionNotes": [],
				"altAnim": false,
				"bpm": 360,
				"changeBPM": false,
				"mustHitSection": true
			},
			{
				"lengthInSteps": 16,
				"typeOfSection": 0,
				"sectionNotes": [],
				"altAnim": false,
				"bpm": 360,
				"changeBPM": false,
				"mustHitSection": true
			},
			{
				"lengthInSteps": 16,
				"typeOfSection": 0,
				"sectionNotes": [],
				"altAnim": false,
				"bpm": 360,
				"changeBPM": false,
				"mustHitSection": true
			},
			{
				"lengthInSteps": 16,
				"typeOfSection": 0,
				"sectionNotes": [],
				"altAnim": false,
				"bpm": 360,
				"changeBPM": false,
				"mustHitSection": true
			},
			{
				"lengthInSteps": 16,
				"typeOfSection": 0,
				"sectionNotes": [],
				"altAnim": false,
				"bpm": 360,
				"changeBPM": false,
				"mustHitSection": true
			},
			{
				"lengthInSteps": 16,
				"typeOfSection": 0,
				"sectionNotes": [],
				"altAnim": false,
				"bpm": 360,
				"changeBPM": false,
				"mustHitSection": true
			},
			{
				"lengthInSteps": 16,
				"typeOfSection": 0,
				"sectionNotes": [],
				"altAnim": false,
				"bpm": 360,
				"changeBPM": false,
				"mustHitSection": true
			},
			{
				"lengthInSteps": 16,
				"typeOfSection": 0,
				"sectionNotes": [],
				"altAnim": false,
				"bpm": 360,
				"changeBPM": false,
				"mustHitSection": true
			},
			{
				"lengthInSteps": 16,
				"typeOfSection": 0,
				"sectionNotes": [],
				"altAnim": false,
				"bpm": 360,
				"changeBPM": false,
				"mustHitSection": true
			},
			{
				"lengthInSteps": 16,
				"typeOfSection": 0,
				"sectionNotes": [],
				"altAnim": false,
				"bpm": 360,
				"changeBPM": false,
				"mustHitSection": true
			},
			{
				"lengthInSteps": 16,
				"typeOfSection": 0,
				"sectionNotes": [],
				"altAnim": false,
				"bpm": 360,
				"changeBPM": false,
				"mustHitSection": true
			},
			{
				"lengthInSteps": 16,
				"typeOfSection": 0,
				"sectionNotes": [],
				"altAnim": false,
				"bpm": 360,
				"changeBPM": false,
				"mustHitSection": true
			},
			{
				"lengthInSteps": 16,
				"typeOfSection": 0,
				"sectionNotes": [],
				"altAnim": false,
				"bpm": 360,
				"changeBPM": false,
				"mustHitSection": true
			},
			{
				"lengthInSteps": 16,
				"typeOfSection": 0,
				"sectionNotes": [],
				"altAnim": false,
				"bpm": 360,
				"changeBPM": false,
				"mustHitSection": true
			},
			{
				"lengthInSteps": 16,
				"typeOfSection": 0,
				"sectionNotes": [],
				"altAnim": false,
				"bpm": 360,
				"changeBPM": false,
				"mustHitSection": true
			},
			{
				"lengthInSteps": 16,
				"typeOfSection": 0,
				"sectionNotes": [],
				"altAnim": false,
				"bpm": 360,
				"changeBPM": false,
				"mustHitSection": true
			},
			{
				"lengthInSteps": 16,
				"typeOfSection": 0,
				"sectionNotes": [],
				"altAnim": false,
				"bpm": 360,
				"changeBPM": false,
				"mustHitSection": true
			},
			{
				"lengthInSteps": 16,
				"typeOfSection": 0,
				"sectionNotes": [],
				"altAnim": false,
				"bpm": 360,
				"changeBPM": false,
				"mustHitSection": true
			},
			{
				"lengthInSteps": 16,
				"typeOfSection": 0,
				"sectionNotes": [],
				"altAnim": false,
				"bpm": 360,
				"changeBPM": false,
				"mustHitSection": true
			},
			{
				"lengthInSteps": 16,
				"typeOfSection": 0,
				"sectionNotes": [],
				"altAnim": false,
				"bpm": 360,
				"changeBPM": false,
				"mustHitSection": true
			},
			{
				"lengthInSteps": 16,
				"typeOfSection": 0,
				"sectionNotes": [],
				"altAnim": false,
				"bpm": 360,
				"changeBPM": false,
				"mustHitSection": true
			},
			{
				"lengthInSteps": 16,
				"typeOfSection": 0,
				"sectionNotes": [],
				"altAnim": false,
				"bpm": 360,
				"changeBPM": false,
				"mustHitSection": true
			},
			{
				"lengthInSteps": 16,
				"typeOfSection": 0,
				"sectionNotes": [],
				"altAnim": false,
				"bpm": 360,
				"changeBPM": false,
				"mustHitSection": true
			},
			{
				"lengthInSteps": 16,
				"typeOfSection": 0,
				"sectionNotes": [],
				"altAnim": false,
				"bpm": 360,
				"changeBPM": false,
				"mustHitSection": true
			},
			{
				"lengthInSteps": 16,
				"typeOfSection": 0,
				"sectionNotes": [],
				"altAnim": false,
				"bpm": 360,
				"changeBPM": false,
				"mustHitSection": true
			},
			{
				"lengthInSteps": 16,
				"typeOfSection": 0,
				"sectionNotes": [],
				"altAnim": false,
				"bpm": 360,
				"changeBPM": false,
				"mustHitSection": true
			},
			{
				"lengthInSteps": 16,
				"typeOfSection": 0,
				"sectionNotes": [],
				"altAnim": false,
				"bpm": 360,
				"changeBPM": false,
				"mustHitSection": true
			},
			{
				"lengthInSteps": 16,
				"typeOfSection": 0,
				"sectionNotes": [],
				"altAnim": false,
				"bpm": 360,
				"changeBPM": false,
				"mustHitSection": true
			},
			{
				"lengthInSteps": 16,
				"typeOfSection": 0,
				"sectionNotes": [],
				"altAnim": false,
				"bpm": 360,
				"changeBPM": false,
				"mustHitSection": true
			},
			{
				"lengthInSteps": 16,
				"typeOfSection": 0,
				"sectionNotes": [],
				"altAnim": false,
				"bpm": 360,
				"changeBPM": false,
				"mustHitSection": true
			},
			{
				"lengthInSteps": 16,
				"typeOfSection": 0,
				"sectionNotes": [],
				"altAnim": false,
				"bpm": 360,
				"changeBPM": false,
				"mustHitSection": true
			},
			{
				"lengthInSteps": 16,
				"typeOfSection": 0,
				"sectionNotes": [],
				"altAnim": false,
				"bpm": 360,
				"changeBPM": false,
				"mustHitSection": true
			},
			{
				"lengthInSteps": 16,
				"typeOfSection": 0,
				"sectionNotes": [],
				"altAnim": false,
				"bpm": 360,
				"changeBPM": false,
				"mustHitSection": true
			},
			{
				"lengthInSteps": 16,
				"typeOfSection": 0,
				"sectionNotes": [],
				"altAnim": false,
				"bpm": 360,
				"changeBPM": false,
				"mustHitSection": true
			},
			{
				"lengthInSteps": 16,
				"typeOfSection": 0,
				"sectionNotes": [],
				"altAnim": false,
				"bpm": 360,
				"changeBPM": false,
				"mustHitSection": true
			},
			{
				"lengthInSteps": 16,
				"typeOfSection": 0,
				"sectionNotes": [],
				"altAnim": false,
				"bpm": 360,
				"changeBPM": false,
				"mustHitSection": true
			},
			{
				"lengthInSteps": 16,
				"typeOfSection": 0,
				"sectionNotes": [],
				"altAnim": false,
				"bpm": 360,
				"changeBPM": false,
				"mustHitSection": true
			},
			{
				"lengthInSteps": 16,
				"typeOfSection": 0,
				"sectionNotes": [],
				"altAnim": false,
				"bpm": 360,
				"changeBPM": false,
				"mustHitSection": true
			},
			{
				"lengthInSteps": 16,
				"typeOfSection": 0,
				"sectionNotes": [],
				"altAnim": false,
				"bpm": 360,
				"changeBPM": false,
				"mustHitSection": true
			},
			{
				"lengthInSteps": 16,
				"typeOfSection": 0,
				"sectionNotes": [],
				"altAnim": false,
				"bpm": 360,
				"changeBPM": false,
				"mustHitSection": true
			},
			{
				"lengthInSteps": 16,
				"typeOfSection": 0,
				"sectionNotes": [],
				"altAnim": false,
				"bpm": 360,
				"changeBPM": false,
				"mustHitSection": true
			},
			{
				"lengthInSteps": 16,
				"typeOfSection": 0,
				"sectionNotes": [],
				"altAnim": false,
				"bpm": 360,
				"changeBPM": false,
				"mustHitSection": true
			},
			{
				"lengthInSteps": 16,
				"typeOfSection": 0,
				"sectionNotes": [],
				"altAnim": false,
				"bpm": 360,
				"changeBPM": false,
				"mustHitSection": true
			},
			{
				"lengthInSteps": 16,
				"typeOfSection": 0,
				"sectionNotes": [],
				"altAnim": false,
				"bpm": 360,
				"changeBPM": false,
				"mustHitSection": true
			},
			{
				"lengthInSteps": 16,
				"typeOfSection": 0,
				"sectionNotes": [],
				"altAnim": false,
				"bpm": 360,
				"changeBPM": false,
				"mustHitSection": true
			},
			{
				"lengthInSteps": 16,
				"typeOfSection": 0,
				"sectionNotes": [],
				"altAnim": false,
				"bpm": 360,
				"changeBPM": false,
				"mustHitSection": true
			},
			{
				"lengthInSteps": 16,
				"typeOfSection": 0,
				"sectionNotes": [],
				"altAnim": false,
				"bpm": 360,
				"changeBPM": false,
				"mustHitSection": true
			},
			{
				"lengthInSteps": 16,
				"typeOfSection": 0,
				"sectionNotes": [],
				"altAnim": false,
				"bpm": 360,
				"changeBPM": false,
				"mustHitSection": true
			},
			{
				"lengthInSteps": 16,
				"typeOfSection": 0,
				"sectionNotes": [],
				"altAnim": false,
				"bpm": 360,
				"changeBPM": false,
				"mustHitSection": true
			},
			{
				"lengthInSteps": 16,
				"typeOfSection": 0,
				"sectionNotes": [],
				"altAnim": false,
				"bpm": 360,
				"changeBPM": false,
				"mustHitSection": true
			},
			{
				"lengthInSteps": 16,
				"typeOfSection": 0,
				"sectionNotes": [],
				"altAnim": false,
				"bpm": 360,
				"changeBPM": false,
				"mustHitSection": true
			},
			{
				"lengthInSteps": 16,
				"typeOfSection": 0,
				"sectionNotes": [],
				"altAnim": false,
				"bpm": 360,
				"changeBPM": false,
				"mustHitSection": true
			},
			{
				"lengthInSteps": 16,
				"typeOfSection": 0,
				"sectionNotes": [],
				"altAnim": false,
				"bpm": 360,
				"changeBPM": false,
				"mustHitSection": true
			},
			{
				"lengthInSteps": 16,
				"typeOfSection": 0,
				"sectionNotes": [],
				"altAnim": false,
				"bpm": 360,
				"changeBPM": false,
				"mustHitSection": true
			},
			{
				"lengthInSteps": 16,
				"typeOfSection": 0,
				"sectionNotes": [],
				"altAnim": false,
				"bpm": 360,
				"changeBPM": false,
				"mustHitSection": true
			},
			{
				"lengthInSteps": 16,
				"typeOfSection": 0,
				"sectionNotes": [],
				"altAnim": false,
				"bpm": 360,
				"changeBPM": false,
				"mustHitSection": true
			},
			{
				"lengthInSteps": 16,
				"typeOfSection": 0,
				"sectionNotes": [],
				"altAnim": false,
				"bpm": 360,
				"changeBPM": false,
				"mustHitSection": true
			},
			{
				"lengthInSteps": 16,
				"typeOfSection": 0,
				"sectionNotes": [],
				"altAnim": false,
				"bpm": 360,
				"changeBPM": false,
				"mustHitSection": true
			},
			{
				"lengthInSteps": 16,
				"typeOfSection": 0,
				"sectionNotes": [],
				"altAnim": false,
				"bpm": 360,
				"changeBPM": false,
				"mustHitSection": true
			},
			{
				"lengthInSteps": 16,
				"typeOfSection": 0,
				"sectionNotes": [],
				"altAnim": false,
				"bpm": 360,
				"changeBPM": false,
				"mustHitSection": true
			},
			{
				"lengthInSteps": 16,
				"typeOfSection": 0,
				"sectionNotes": [],
				"altAnim": false,
				"bpm": 360,
				"changeBPM": false,
				"mustHitSection": true
			},
			{
				"lengthInSteps": 16,
				"typeOfSection": 0,
				"sectionNotes": [],
				"altAnim": false,
				"bpm": 360,
				"changeBPM": false,
				"mustHitSection": true
			},
			{
				"lengthInSteps": 16,
				"typeOfSection": 0,
				"sectionNotes": [],
				"altAnim": false,
				"bpm": 360,
				"changeBPM": false,
				"mustHitSection": true
			},
			{
				"lengthInSteps": 16,
				"typeOfSection": 0,
				"sectionNotes": [],
				"altAnim": false,
				"bpm": 360,
				"changeBPM": false,
				"mustHitSection": true
			},
			{
				"lengthInSteps": 16,
				"typeOfSection": 0,
				"sectionNotes": [],
				"altAnim": false,
				"bpm": 360,
				"changeBPM": false,
				"mustHitSection": true
			},
			{
				"lengthInSteps": 16,
				"typeOfSection": 0,
				"sectionNotes": [],
				"altAnim": false,
				"bpm": 360,
				"changeBPM": false,
				"mustHitSection": true
			},
			{
				"lengthInSteps": 16,
				"typeOfSection": 0,
				"sectionNotes": [],
				"altAnim": false,
				"bpm": 360,
				"changeBPM": false,
				"mustHitSection": true
			},
			{
				"lengthInSteps": 16,
				"typeOfSection": 0,
				"sectionNotes": [],
				"altAnim": false,
				"bpm": 360,
				"changeBPM": false,
				"mustHitSection": true
			},
			{
				"lengthInSteps": 16,
				"typeOfSection": 0,
				"sectionNotes": [],
				"altAnim": false,
				"bpm": 360,
				"changeBPM": false,
				"mustHitSection": true
			},
			{
				"lengthInSteps": 16,
				"typeOfSection": 0,
				"sectionNotes": [],
				"altAnim": false,
				"bpm": 360,
				"changeBPM": false,
				"mustHitSection": true
			},
			{
				"lengthInSteps": 16,
				"typeOfSection": 0,
				"sectionNotes": [],
				"altAnim": false,
				"bpm": 360,
				"changeBPM": false,
				"mustHitSection": true
			},
			{
				"lengthInSteps": 16,
				"typeOfSection": 0,
				"sectionNotes": [],
				"altAnim": false,
				"bpm": 360,
				"changeBPM": false,
				"mustHitSection": true
			},
			{
				"lengthInSteps": 16,
				"typeOfSection": 0,
				"sectionNotes": [],
				"altAnim": false,
				"bpm": 360,
				"changeBPM": false,
				"mustHitSection": true
			},
			{
				"lengthInSteps": 16,
				"typeOfSection": 0,
				"sectionNotes": [],
				"altAnim": false,
				"bpm": 360,
				"changeBPM": false,
				"mustHitSection": true
			},
			{
				"lengthInSteps": 16,
				"typeOfSection": 0,
				"sectionNotes": [],
				"altAnim": false,
				"bpm": 360,
				"changeBPM": false,
				"mustHitSection": true
			},
			{
				"lengthInSteps": 16,
				"typeOfSection": 0,
				"sectionNotes": [],
				"altAnim": false,
				"bpm": 360,
				"changeBPM": false,
				"mustHitSection": true
			},
			{
				"lengthInSteps": 16,
				"typeOfSection": 0,
				"sectionNotes": [],
				"altAnim": false,
				"bpm": 360,
				"changeBPM": false,
				"mustHitSection": true
			},
			{
				"lengthInSteps": 16,
				"typeOfSection": 0,
				"sectionNotes": [],
				"altAnim": false,
				"bpm": 360,
				"changeBPM": false,
				"mustHitSection": true
			},
			{
				"lengthInSteps": 16,
				"typeOfSection": 0,
				"sectionNotes": [],
				"altAnim": false,
				"bpm": 360,
				"changeBPM": false,
				"mustHitSection": true
			},
			{
				"lengthInSteps": 16,
				"typeOfSection": 0,
				"sectionNotes": [],
				"altAnim": false,
				"bpm": 360,
				"changeBPM": false,
				"mustHitSection": true
			},
			{
				"lengthInSteps": 16,
				"typeOfSection": 0,
				"sectionNotes": [],
				"altAnim": false,
				"bpm": 360,
				"changeBPM": false,
				"mustHitSection": true
			},
			{
				"lengthInSteps": 16,
				"typeOfSection": 0,
				"sectionNotes": [],
				"altAnim": false,
				"bpm": 360,
				"changeBPM": false,
				"mustHitSection": true
			},
			{
				"lengthInSteps": 16,
				"typeOfSection": 0,
				"sectionNotes": [],
				"altAnim": false,
				"bpm": 360,
				"changeBPM": false,
				"mustHitSection": true
			},
			{
				"lengthInSteps": 16,
				"typeOfSection": 0,
				"sectionNotes": [],
				"altAnim": false,
				"bpm": 360,
				"changeBPM": false,
				"mustHitSection": true
			},
			{
				"lengthInSteps": 16,
				"typeOfSection": 0,
				"sectionNotes": [],
				"altAnim": false,
				"bpm": 360,
				"changeBPM": false,
				"mustHitSection": true
			},
			{
				"lengthInSteps": 16,
				"typeOfSection": 0,
				"sectionNotes": [],
				"altAnim": false,
				"bpm": 360,
				"changeBPM": false,
				"mustHitSection": true
			},
			{
				"lengthInSteps": 16,
				"typeOfSection": 0,
				"sectionNotes": [],
				"altAnim": false,
				"bpm": 360,
				"changeBPM": false,
				"mustHitSection": true
			},
			{
				"lengthInSteps": 16,
				"typeOfSection": 0,
				"sectionNotes": [],
				"altAnim": false,
				"bpm": 360,
				"changeBPM": false,
				"mustHitSection": true
			},
			{
				"lengthInSteps": 16,
				"typeOfSection": 0,
				"sectionNotes": [],
				"altAnim": false,
				"bpm": 360,
				"changeBPM": false,
				"mustHitSection": true
			},
			{
				"lengthInSteps": 16,
				"typeOfSection": 0,
				"sectionNotes": [],
				"altAnim": false,
				"bpm": 360,
				"changeBPM": false,
				"mustHitSection": true
			},
			{
				"lengthInSteps": 16,
				"typeOfSection": 0,
				"sectionNotes": [],
				"altAnim": false,
				"bpm": 360,
				"changeBPM": false,
				"mustHitSection": true
			},
			{
				"lengthInSteps": 16,
				"typeOfSection": 0,
				"sectionNotes": [],
				"altAnim": false,
				"bpm": 360,
				"changeBPM": false,
				"mustHitSection": true
			},
			{
				"lengthInSteps": 16,
				"typeOfSection": 0,
				"sectionNotes": [],
				"altAnim": false,
				"bpm": 360,
				"changeBPM": false,
				"mustHitSection": true
			},
			{
				"lengthInSteps": 16,
				"typeOfSection": 0,
				"sectionNotes": [],
				"altAnim": false,
				"bpm": 360,
				"changeBPM": false,
				"mustHitSection": true
			},
			{
				"lengthInSteps": 16,
				"typeOfSection": 0,
				"sectionNotes": [],
				"altAnim": false,
				"bpm": 360,
				"changeBPM": false,
				"mustHitSection": true
			},
			{
				"lengthInSteps": 16,
				"typeOfSection": 0,
				"sectionNotes": [],
				"altAnim": false,
				"bpm": 360,
				"changeBPM": false,
				"mustHitSection": true
			},
			{
				"lengthInSteps": 16,
				"typeOfSection": 0,
				"sectionNotes": [],
				"altAnim": false,
				"bpm": 360,
				"changeBPM": false,
				"mustHitSection": true
			},
			{
				"lengthInSteps": 16,
				"typeOfSection": 0,
				"sectionNotes": [],
				"altAnim": false,
				"bpm": 360,
				"changeBPM": false,
				"mustHitSection": true
			},
			{
				"lengthInSteps": 16,
				"typeOfSection": 0,
				"sectionNotes": [],
				"altAnim": false,
				"bpm": 360,
				"changeBPM": false,
				"mustHitSection": true
			},
			{
				"lengthInSteps": 16,
				"typeOfSection": 0,
				"sectionNotes": [],
				"altAnim": false,
				"bpm": 360,
				"changeBPM": false,
				"mustHitSection": true
			},
			{
				"lengthInSteps": 16,
				"typeOfSection": 0,
				"sectionNotes": [],
				"altAnim": false,
				"bpm": 360,
				"changeBPM": false,
				"mustHitSection": true
			},
			{
				"lengthInSteps": 16,
				"typeOfSection": 0,
				"sectionNotes": [],
				"altAnim": false,
				"bpm": 360,
				"changeBPM": false,
				"mustHitSection": true
			},
			{
				"lengthInSteps": 16,
				"typeOfSection": 0,
				"sectionNotes": [],
				"altAnim": false,
				"bpm": 360,
				"changeBPM": false,
				"mustHitSection": true
			},
			{
				"lengthInSteps": 16,
				"typeOfSection": 0,
				"sectionNotes": [],
				"altAnim": false,
				"bpm": 360,
				"changeBPM": false,
				"mustHitSection": true
			},
			{
				"lengthInSteps": 16,
				"typeOfSection": 0,
				"sectionNotes": [],
				"altAnim": false,
				"bpm": 360,
				"changeBPM": false,
				"mustHitSection": true
			},
			{
				"lengthInSteps": 16,
				"typeOfSection": 0,
				"sectionNotes": [],
				"altAnim": false,
				"bpm": 360,
				"changeBPM": false,
				"mustHitSection": true
			},
			{
				"lengthInSteps": 16,
				"typeOfSection": 0,
				"sectionNotes": [],
				"altAnim": false,
				"bpm": 360,
				"changeBPM": false,
				"mustHitSection": true
			},
			{
				"lengthInSteps": 16,
				"typeOfSection": 0,
				"sectionNotes": [],
				"altAnim": false,
				"bpm": 360,
				"changeBPM": false,
				"mustHitSection": true
			},
			{
				"lengthInSteps": 16,
				"typeOfSection": 0,
				"sectionNotes": [],
				"altAnim": false,
				"bpm": 360,
				"changeBPM": false,
				"mustHitSection": true
			},
			{
				"lengthInSteps": 16,
				"typeOfSection": 0,
				"sectionNotes": [],
				"altAnim": false,
				"bpm": 360,
				"changeBPM": false,
				"mustHitSection": true
			},
			{
				"lengthInSteps": 16,
				"typeOfSection": 0,
				"sectionNotes": [],
				"altAnim": false,
				"bpm": 360,
				"changeBPM": false,
				"mustHitSection": true
			},
			{
				"lengthInSteps": 16,
				"typeOfSection": 0,
				"sectionNotes": [],
				"altAnim": false,
				"bpm": 360,
				"changeBPM": false,
				"mustHitSection": true
			},
			{
				"lengthInSteps": 16,
				"typeOfSection": 0,
				"sectionNotes": [],
				"altAnim": false,
				"bpm": 360,
				"changeBPM": false,
				"mustHitSection": true
			},
			{
				"lengthInSteps": 16,
				"typeOfSection": 0,
				"sectionNotes": [],
				"altAnim": false,
				"bpm": 360,
				"changeBPM": false,
				"mustHitSection": true
			},
			{
				"lengthInSteps": 16,
				"typeOfSection": 0,
				"sectionNotes": [],
				"altAnim": false,
				"bpm": 360,
				"changeBPM": false,
				"mustHitSection": true
			},
			{
				"lengthInSteps": 16,
				"typeOfSection": 0,
				"sectionNotes": [],
				"altAnim": false,
				"bpm": 360,
				"changeBPM": false,
				"mustHitSection": true
			},
			{
				"lengthInSteps": 16,
				"typeOfSection": 0,
				"sectionNotes": [],
				"altAnim": false,
				"bpm": 360,
				"changeBPM": false,
				"mustHitSection": true
			},
			{
				"lengthInSteps": 16,
				"typeOfSection": 0,
				"sectionNotes": [],
				"altAnim": false,
				"bpm": 360,
				"changeBPM": false,
				"mustHitSection": true
			},
			{
				"lengthInSteps": 16,
				"typeOfSection": 0,
				"sectionNotes": [],
				"altAnim": false,
				"bpm": 360,
				"changeBPM": false,
				"mustHitSection": true
			},
			{
				"lengthInSteps": 16,
				"typeOfSection": 0,
				"sectionNotes": [],
				"altAnim": false,
				"bpm": 360,
				"changeBPM": false,
				"mustHitSection": true
			},
			{
				"lengthInSteps": 16,
				"typeOfSection": 0,
				"sectionNotes": [],
				"altAnim": false,
				"bpm": 360,
				"changeBPM": false,
				"mustHitSection": true
			},
			{
				"lengthInSteps": 16,
				"typeOfSection": 0,
				"sectionNotes": [],
				"altAnim": false,
				"bpm": 360,
				"changeBPM": false,
				"mustHitSection": true
			},
			{
				"lengthInSteps": 16,
				"typeOfSection": 0,
				"sectionNotes": [],
				"altAnim": false,
				"bpm": 360,
				"changeBPM": false,
				"mustHitSection": true
			},
			{
				"lengthInSteps": 16,
				"typeOfSection": 0,
				"sectionNotes": [],
				"altAnim": false,
				"bpm": 360,
				"changeBPM": false,
				"mustHitSection": true
			},
			{
				"lengthInSteps": 16,
				"typeOfSection": 0,
				"sectionNotes": [],
				"altAnim": false,
				"bpm": 360,
				"changeBPM": false,
				"mustHitSection": true
			},
			{
				"lengthInSteps": 16,
				"typeOfSection": 0,
				"sectionNotes": [],
				"altAnim": false,
				"bpm": 360,
				"changeBPM": false,
				"mustHitSection": true
			},
			{
				"lengthInSteps": 16,
				"typeOfSection": 0,
				"sectionNotes": [],
				"altAnim": false,
				"bpm": 360,
				"changeBPM": false,
				"mustHitSection": true
			},
			{
				"lengthInSteps": 16,
				"typeOfSection": 0,
				"sectionNotes": [],
				"altAnim": false,
				"bpm": 360,
				"changeBPM": false,
				"mustHitSection": true
			},
			{
				"lengthInSteps": 16,
				"typeOfSection": 0,
				"sectionNotes": [],
				"altAnim": false,
				"bpm": 360,
				"changeBPM": false,
				"mustHitSection": true
			},
			{
				"lengthInSteps": 16,
				"typeOfSection": 0,
				"sectionNotes": [],
				"altAnim": false,
				"bpm": 360,
				"changeBPM": false,
				"mustHitSection": true
			},
			{
				"lengthInSteps": 16,
				"typeOfSection": 0,
				"sectionNotes": [],
				"altAnim": false,
				"bpm": 360,
				"changeBPM": false,
				"mustHitSection": true
			},
			{
				"lengthInSteps": 16,
				"typeOfSection": 0,
				"sectionNotes": [],
				"altAnim": false,
				"bpm": 360,
				"changeBPM": false,
				"mustHitSection": true
			},
			{
				"lengthInSteps": 16,
				"typeOfSection": 0,
				"sectionNotes": [],
				"altAnim": false,
				"bpm": 360,
				"changeBPM": false,
				"mustHitSection": true
			},
			{
				"lengthInSteps": 16,
				"typeOfSection": 0,
				"sectionNotes": [],
				"altAnim": false,
				"bpm": 360,
				"changeBPM": false,
				"mustHitSection": true
			},
			{
				"lengthInSteps": 16,
				"typeOfSection": 0,
				"sectionNotes": [],
				"altAnim": false,
				"bpm": 360,
				"changeBPM": false,
				"mustHitSection": true
			},
			{
				"lengthInSteps": 16,
				"typeOfSection": 0,
				"sectionNotes": [],
				"altAnim": false,
				"bpm": 360,
				"changeBPM": false,
				"mustHitSection": true
			},
			{
				"lengthInSteps": 16,
				"typeOfSection": 0,
				"sectionNotes": [],
				"altAnim": false,
				"bpm": 360,
				"changeBPM": false,
				"mustHitSection": true
			},
			{
				"lengthInSteps": 16,
				"typeOfSection": 0,
				"sectionNotes": [],
				"altAnim": false,
				"bpm": 360,
				"changeBPM": false,
				"mustHitSection": true
			},
			{
				"lengthInSteps": 16,
				"typeOfSection": 0,
				"sectionNotes": [],
				"altAnim": false,
				"bpm": 360,
				"changeBPM": false,
				"mustHitSection": true
			},
			{
				"lengthInSteps": 16,
				"typeOfSection": 0,
				"sectionNotes": [],
				"altAnim": false,
				"bpm": 360,
				"changeBPM": false,
				"mustHitSection": true
			},
			{
				"lengthInSteps": 16,
				"typeOfSection": 0,
				"sectionNotes": [],
				"altAnim": false,
				"bpm": 360,
				"changeBPM": false,
				"mustHitSection": true
			},
			{
				"lengthInSteps": 16,
				"typeOfSection": 0,
				"sectionNotes": [],
				"altAnim": false,
				"bpm": 360,
				"changeBPM": false,
				"mustHitSection": true
			},
			{
				"lengthInSteps": 16,
				"typeOfSection": 0,
				"sectionNotes": [],
				"altAnim": false,
				"bpm": 360,
				"changeBPM": false,
				"mustHitSection": true
			},
			{
				"lengthInSteps": 16,
				"typeOfSection": 0,
				"sectionNotes": [],
				"altAnim": false,
				"bpm": 360,
				"changeBPM": false,
				"mustHitSection": true
			},
			{
				"lengthInSteps": 16,
				"typeOfSection": 0,
				"sectionNotes": [],
				"altAnim": false,
				"bpm": 360,
				"changeBPM": false,
				"mustHitSection": true
			},
			{
				"lengthInSteps": 16,
				"typeOfSection": 0,
				"sectionNotes": [],
				"altAnim": false,
				"bpm": 360,
				"changeBPM": false,
				"mustHitSection": true
			},
			{
				"lengthInSteps": 16,
				"typeOfSection": 0,
				"sectionNotes": [],
				"altAnim": false,
				"bpm": 360,
				"changeBPM": false,
				"mustHitSection": true
			},
			{
				"lengthInSteps": 16,
				"typeOfSection": 0,
				"sectionNotes": [],
				"altAnim": false,
				"bpm": 360,
				"changeBPM": false,
				"mustHitSection": true
			},
			{
				"lengthInSteps": 16,
				"typeOfSection": 0,
				"sectionNotes": [],
				"altAnim": false,
				"bpm": 360,
				"changeBPM": false,
				"mustHitSection": true
			},
			{
				"lengthInSteps": 16,
				"typeOfSection": 0,
				"sectionNotes": [],
				"altAnim": false,
				"bpm": 360,
				"changeBPM": false,
				"mustHitSection": true
			},
			{
				"lengthInSteps": 16,
				"typeOfSection": 0,
				"sectionNotes": [],
				"altAnim": false,
				"bpm": 360,
				"changeBPM": false,
				"mustHitSection": true
			},
			{
				"lengthInSteps": 16,
				"typeOfSection": 0,
				"sectionNotes": [],
				"altAnim": false,
				"bpm": 360,
				"changeBPM": false,
				"mustHitSection": true
			},
			{
				"lengthInSteps": 16,
				"typeOfSection": 0,
				"sectionNotes": [],
				"altAnim": false,
				"bpm": 360,
				"changeBPM": false,
				"mustHitSection": true
			},
			{
				"lengthInSteps": 16,
				"typeOfSection": 0,
				"sectionNotes": [],
				"altAnim": false,
				"bpm": 360,
				"changeBPM": false,
				"mustHitSection": true
			},
			{
				"lengthInSteps": 16,
				"typeOfSection": 0,
				"sectionNotes": [],
				"altAnim": false,
				"bpm": 360,
				"changeBPM": false,
				"mustHitSection": true
			},
			{
				"lengthInSteps": 16,
				"typeOfSection": 0,
				"sectionNotes": [],
				"altAnim": false,
				"bpm": 360,
				"changeBPM": false,
				"mustHitSection": true
			},
			{
				"lengthInSteps": 16,
				"typeOfSection": 0,
				"sectionNotes": [],
				"altAnim": false,
				"bpm": 360,
				"changeBPM": false,
				"mustHitSection": true
			},
			{
				"lengthInSteps": 16,
				"typeOfSection": 0,
				"sectionNotes": [],
				"altAnim": false,
				"bpm": 360,
				"changeBPM": false,
				"mustHitSection": true
			},
			{
				"lengthInSteps": 16,
				"typeOfSection": 0,
				"sectionNotes": [],
				"altAnim": false,
				"bpm": 360,
				"changeBPM": false,
				"mustHitSection": true
			},
			{
				"lengthInSteps": 16,
				"typeOfSection": 0,
				"sectionNotes": [],
				"altAnim": false,
				"bpm": 360,
				"changeBPM": false,
				"mustHitSection": true
			},
			{
				"lengthInSteps": 16,
				"typeOfSection": 0,
				"sectionNotes": [],
				"altAnim": false,
				"bpm": 360,
				"changeBPM": false,
				"mustHitSection": true
			},
			{
				"lengthInSteps": 16,
				"typeOfSection": 0,
				"sectionNotes": [],
				"altAnim": false,
				"bpm": 360,
				"changeBPM": false,
				"mustHitSection": true
			},
			{
				"lengthInSteps": 16,
				"typeOfSection": 0,
				"sectionNotes": [],
				"altAnim": false,
				"bpm": 360,
				"changeBPM": false,
				"mustHitSection": true
			},
			{
				"lengthInSteps": 16,
				"typeOfSection": 0,
				"sectionNotes": [],
				"altAnim": false,
				"bpm": 360,
				"changeBPM": false,
				"mustHitSection": true
			},
			{
				"lengthInSteps": 16,
				"typeOfSection": 0,
				"sectionNotes": [],
				"altAnim": false,
				"bpm": 360,
				"changeBPM": false,
				"mustHitSection": true
			},
			{
				"lengthInSteps": 16,
				"typeOfSection": 0,
				"sectionNotes": [],
				"altAnim": false,
				"bpm": 360,
				"changeBPM": false,
				"mustHitSection": true
			},
			{
				"lengthInSteps": 16,
				"typeOfSection": 0,
				"sectionNotes": [],
				"altAnim": false,
				"bpm": 360,
				"changeBPM": false,
				"mustHitSection": true
			},
			{
				"lengthInSteps": 16,
				"typeOfSection": 0,
				"sectionNotes": [],
				"altAnim": false,
				"bpm": 360,
				"changeBPM": false,
				"mustHitSection": true
			},
			{
				"lengthInSteps": 16,
				"typeOfSection": 0,
				"sectionNotes": [],
				"altAnim": false,
				"bpm": 360,
				"changeBPM": false,
				"mustHitSection": true
			},
			{
				"lengthInSteps": 16,
				"typeOfSection": 0,
				"sectionNotes": [],
				"altAnim": false,
				"bpm": 360,
				"changeBPM": false,
				"mustHitSection": true
			},
			{
				"lengthInSteps": 16,
				"typeOfSection": 0,
				"sectionNotes": [],
				"altAnim": false,
				"bpm": 360,
				"changeBPM": false,
				"mustHitSection": true
			},
			{
				"lengthInSteps": 16,
				"typeOfSection": 0,
				"sectionNotes": [],
				"altAnim": false,
				"bpm": 360,
				"changeBPM": false,
				"mustHitSection": true
			},
			{
				"lengthInSteps": 16,
				"typeOfSection": 0,
				"sectionNotes": [],
				"altAnim": false,
				"bpm": 360,
				"changeBPM": false,
				"mustHitSection": true
			},
			{
				"lengthInSteps": 16,
				"typeOfSection": 0,
				"sectionNotes": [],
				"altAnim": false,
				"bpm": 360,
				"changeBPM": false,
				"mustHitSection": true
			},
			{
				"lengthInSteps": 16,
				"typeOfSection": 0,
				"sectionNotes": [],
				"altAnim": false,
				"bpm": 360,
				"changeBPM": false,
				"mustHitSection": true
			},
			{
				"lengthInSteps": 16,
				"typeOfSection": 0,
				"sectionNotes": [],
				"altAnim": false,
				"bpm": 360,
				"changeBPM": false,
				"mustHitSection": true
			},
			{
				"lengthInSteps": 16,
				"typeOfSection": 0,
				"sectionNotes": [],
				"altAnim": false,
				"bpm": 360,
				"changeBPM": false,
				"mustHitSection": true
			},
			{
				"lengthInSteps": 16,
				"typeOfSection": 0,
				"sectionNotes": [],
				"altAnim": false,
				"bpm": 360,
				"changeBPM": false,
				"mustHitSection": true
			},
			{
				"lengthInSteps": 16,
				"typeOfSection": 0,
				"sectionNotes": [],
				"altAnim": false,
				"bpm": 360,
				"changeBPM": false,
				"mustHitSection": true
			},
			{
				"lengthInSteps": 16,
				"typeOfSection": 0,
				"sectionNotes": [],
				"altAnim": false,
				"bpm": 360,
				"changeBPM": false,
				"mustHitSection": true
			},
			{
				"lengthInSteps": 16,
				"typeOfSection": 0,
				"sectionNotes": [],
				"altAnim": false,
				"bpm": 360,
				"changeBPM": false,
				"mustHitSection": true
			},
			{
				"lengthInSteps": 16,
				"typeOfSection": 0,
				"sectionNotes": [],
				"altAnim": false,
				"bpm": 360,
				"changeBPM": false,
				"mustHitSection": true
			},
			{
				"lengthInSteps": 16,
				"typeOfSection": 0,
				"sectionNotes": [],
				"altAnim": false,
				"bpm": 360,
				"changeBPM": false,
				"mustHitSection": true
			},
			{
				"lengthInSteps": 16,
				"typeOfSection": 0,
				"sectionNotes": [],
				"altAnim": false,
				"bpm": 360,
				"changeBPM": false,
				"mustHitSection": true
			},
			{
				"lengthInSteps": 16,
				"typeOfSection": 0,
				"sectionNotes": [],
				"altAnim": false,
				"bpm": 360,
				"changeBPM": false,
				"mustHitSection": true
			},
			{
				"lengthInSteps": 16,
				"typeOfSection": 0,
				"sectionNotes": [],
				"altAnim": false,
				"bpm": 360,
				"changeBPM": false,
				"mustHitSection": true
			},
			{
				"lengthInSteps": 16,
				"typeOfSection": 0,
				"sectionNotes": [],
				"altAnim": false,
				"bpm": 360,
				"changeBPM": false,
				"mustHitSection": true
			},
			{
				"lengthInSteps": 16,
				"typeOfSection": 0,
				"sectionNotes": [],
				"altAnim": false,
				"bpm": 360,
				"changeBPM": false,
				"mustHitSection": true
			},
			{
				"sectionNotes": [],
				"typeOfSection": 0,
				"lengthInSteps": 16,
				"altAnim": false,
				"mustHitSection": true,
				"changeBPM": false,
				"bpm": 345
			},
			{
				"sectionNotes": [],
				"typeOfSection": 0,
				"lengthInSteps": 16,
				"altAnim": false,
				"mustHitSection": true,
				"changeBPM": false,
				"bpm": 175
			},
			{
				"sectionNotes": [],
				"typeOfSection": 0,
				"lengthInSteps": 16,
				"altAnim": false,
				"mustHitSection": true,
				"changeBPM": false,
				"bpm": 175
			},
			{
				"lengthInSteps": 16,
				"typeOfSection": 0,
				"sectionNotes": [],
				"altAnim": false,
				"bpm": 175,
				"changeBPM": false,
				"mustHitSection": true
			},
			{
				"lengthInSteps": 16,
				"typeOfSection": 0,
				"sectionNotes": [],
				"altAnim": false,
				"bpm": 175,
				"changeBPM": false,
				"mustHitSection": true
			},
			{
				"lengthInSteps": 16,
				"typeOfSection": 0,
				"sectionNotes": [],
				"altAnim": false,
				"bpm": 175,
				"changeBPM": false,
				"mustHitSection": true
			},
			{
				"sectionNotes": [],
				"typeOfSection": 0,
				"lengthInSteps": 16,
				"altAnim": false,
				"mustHitSection": true,
				"changeBPM": false,
				"bpm": 175
			},
			{
				"lengthInSteps": 16,
				"typeOfSection": 0,
				"sectionNotes": [],
				"altAnim": false,
				"bpm": 175,
				"changeBPM": false,
				"mustHitSection": true
			},
			{
				"sectionNotes": [],
				"typeOfSection": 0,
				"lengthInSteps": 16,
				"gfSection": false,
				"altAnim": false,
				"mustHitSection": true,
				"changeBPM": false,
				"bpm": 175
			},
			{
				"lengthInSteps": 16,
				"typeOfSection": 0,
				"sectionNotes": [],
				"altAnim": false,
				"gfSection": false,
				"bpm": 175,
				"changeBPM": false,
				"mustHitSection": true
			},
			{
				"sectionNotes": [],
				"typeOfSection": 0,
				"lengthInSteps": 16,
				"gfSection": false,
				"altAnim": false,
				"mustHitSection": true,
				"changeBPM": false,
				"bpm": 100
			},
			{
				"gfSection": false,
				"altAnim": false,
				"typeOfSection": 0,
				"sectionNotes": [],
				"bpm": 100,
				"sectionBeats": 4,
				"changeBPM": false,
				"mustHitSection": true
			}
		],
		"gfVersion": "gf",
		"events": [],
		"player3": null,
		"mania": 3,
		"song": "life-is-fun",
		"stage": "stage",
		"validScore": true,
		"needsVoices": false,
		"speed": 2.4,
		"bpm": 110
	}
}